{
	"1761196": {
		"id": 1761196,
		"description": "KN SLICER 9IN BLUE",
		"name": "1761196 KN SLICER 9IN BLUE",
		"parentID": "PRO-1761196",
		"type": "SKU",
		"Drop Ship Ind": "No",
		"Web Active Ind": "Yes",
		"Bevel": "Double",
		"Bevel Angle": 16,
		"Blade Edge": "Straight",
		"Blade Length": "9\"",
		"Blade Material": "Stainless Steel",
		"Total Length": "",
		"Core Material": "Blue Carbon",
		"Handle Material": "Grey PakkaWood",
		"Layers in the Blade": 3,
		"Rockwell": 61,
		"Stamped or Forged": "Forged",
		"Tang Type": "Partial",
		"Collection": "Blue",
		"Country of Origin": "Japan",
		"Warranty": "lifetime",
		"Web Brand": "Shun",
		"Care & Usage": "<ul>\n<li>Hand wash only with mild soap</li>\n<li>Dry knife completely before storing. In coastal areas or in other areas in which knife will be exposed to salt air, oil blade lightly with food-grade mineral oil to prevent rusting</li>\n</ul>",
		"What's in the Box": ""
	},
	"length": 1,
	"id": "PRO-1761196"
}
