{
	"3661576": {
		"id": 3661576,
		"description": "KN SET 3PC CHEF RF DS",
		"name": "3661576 KN SET 3PC CHEF RF DS",
		"parentID": "PRO-3661576",
		"type": "SKU",
		"Drop Ship Ind": "Yes",
		"Web Active Ind": "Yes",
		"Bevel": "",
		"Bevel Angle": "18-20",
		"Blade Edge": "",
		"Blade Length": "",
		"Blade Material": "High-Carbon Stainless Steel 4116",
		"Total Length": "",
		"Core Material": "High-Carbon Stainless Steel 4116",
		"Handle Material": "Rosewood",
		"Layers in the Blade": 1,
		"Rockwell": "58",
		"Stamped or Forged": "Forged",
		"Tang Type": "Full",
		"Collection": "Rosewood Forged",
		"Country of Origin": "USA",
		"Warranty": "Limited Lifetime Warranty",
		"Web Brand": "Lamson",
		"Care & Usage": "<ul>\n<li>Hand wash only</li>\n</ul>",
		"What's in the Box": "<ul>\n<li>3.5&#34; paring knife</li>\n<li>6&#34; utility knife</li>\n<li>8&#34; chef&#8217;s knife</li>\n</ul>"
	},
	"length": 1,
	"id": "PRO-3661576"
}
